ueconfigparser/__init__.py
ueconfigparser/config_parser.py
ueconfigparser-1.2.0.dist-info/LICENSE
ueconfigparser-1.2.0.dist-info/METADATA
ueconfigparser-1.2.0.dist-info/WHEEL
ueconfigparser-1.2.0.dist-info/top_level.txt
ueconfigparser-1.2.0.dist-info/RECORD
